{
  "body": {
    "tag": "BODY",
    "classes": "",
    "id": "",
    "text": "Flow\ntv\nFlow TV\nhelp_outlined\nFlow Help Center\nFlow Help Center\nmore_vert\nULTRA\n",
    "background-color": "rgb(0, 0, 0)",
    "background-image": "none",
    "color": "rgb(0, 0, 0)",
    "font-family": "\"Google Sans Text\"",
    "font-size": "16px",
    "font-weight": "400",
    "letter-spacing": "normal",
    "line-height": "24px",
    "padding": "0px",
    "padding-top": "0px",
    "padding-right": "0px",
    "padding-bottom": "0px",
    "padding-left": "0px",
    "margin": "0px",
    "margin-top": "0px",
    "margin-right": "0px",
    "margin-bottom": "0px",
    "margin-left": "0px",
    "border": "0px none rgb(0, 0, 0)",
    "border-radius": "0px",
    "border-color": "rgb(0, 0, 0)",
    "border-width": "0px",
    "border-style": "none",
    "width": "1440px",
    "height": "900px",
    "max-width": "none",
    "min-width": "0px",
    "display": "block",
    "grid-template-columns": "none",
    "grid-template-rows": "none",
    "gap": "normal",
    "flex-direction": "row",
    "justify-content": "normal",
    "align-items": "normal",
    "box-shadow": "none",
    "backdrop-filter": "none",
    "opacity": "1",
    "position": "static",
    "top": "auto",
    "right": "auto",
    "bottom": "auto",
    "left": "auto",
    "z-index": "auto",
    "overflow": "visible",
    "bbox": {
      "x": 0,
      "y": 0,
      "width": 1440,
      "height": 900,
      "top": 0,
      "right": 1440,
      "bottom": 900,
      "left": 0
    }
  },
  "topbar": {
    "tag": "DIV",
    "classes": "grecaptcha-badge",
    "id": "",
    "text": "",
    "background-color": "rgba(0, 0, 0, 0)",
    "background-image": "none",
    "color": "rgb(0, 0, 0)",
    "font-family": "\"Google Sans Text\"",
    "font-size": "16px",
    "font-weight": "400",
    "letter-spacing": "normal",
    "line-height": "24px",
    "padding": "0px",
    "padding-top": "0px",
    "padding-right": "0px",
    "padding-bottom": "0px",
    "padding-left": "0px",
    "margin": "0px",
    "margin-top": "0px",
    "margin-right": "0px",
    "margin-bottom": "0px",
    "margin-left": "0px",
    "border": "0px none rgb(0, 0, 0)",
    "border-radius": "2px",
    "border-color": "rgb(0, 0, 0)",
    "border-width": "0px",
    "border-style": "none",
    "width": "256px",
    "height": "60px",
    "max-width": "none",
    "min-width": "0px",
    "display": "block",
    "grid-template-columns": "none",
    "grid-template-rows": "none",
    "gap": "normal",
    "flex-direction": "row",
    "justify-content": "normal",
    "align-items": "normal",
    "box-shadow": "rgb(128, 128, 128) 0px 0px 5px 0px",
    "backdrop-filter": "none",
    "opacity": "1",
    "position": "fixed",
    "top": "826px",
    "right": "-186px",
    "bottom": "14px",
    "left": "1370px",
    "z-index": "auto",
    "overflow": "hidden",
    "bbox": {
      "x": 1370,
      "y": 826,
      "width": 256,
      "height": 60,
      "top": 826,
      "right": 1626,
      "bottom": 886,
      "left": 1370
    }
  },
  "virtList": {
    "tag": "DIV",
    "classes": "",
    "id": "",
    "text": "Apr 26, 05:55 PM\nedit\nEdit project\ndelete\nDelete project\nApr 26, 05:39 PM\nedit\nE",
    "background-color": "rgba(0, 0, 0, 0)",
    "background-image": "none",
    "color": "rgb(0, 0, 0)",
    "font-family": "\"Google Sans Text\"",
    "font-size": "16px",
    "font-weight": "400",
    "letter-spacing": "normal",
    "line-height": "24px",
    "padding": "0px 0px 1276px",
    "padding-top": "0px",
    "padding-right": "0px",
    "padding-bottom": "1276px",
    "padding-left": "0px",
    "margin": "0px",
    "margin-top": "0px",
    "margin-right": "0px",
    "margin-bottom": "0px",
    "margin-left": "0px",
    "border": "0px none rgb(0, 0, 0)",
    "border-radius": "0px",
    "border-color": "rgb(0, 0, 0)",
    "border-width": "0px",
    "border-style": "none",
    "width": "1432px",
    "height": "2233px",
    "max-width": "none",
    "min-width": "0px",
    "display": "block",
    "grid-template-columns": "none",
    "grid-template-rows": "none",
    "gap": "normal",
    "flex-direction": "row",
    "justify-content": "normal",
    "align-items": "normal",
    "box-shadow": "none",
    "backdrop-filter": "none",
    "opacity": "1",
    "position": "static",
    "top": "auto",
    "right": "auto",
    "bottom": "auto",
    "left": "auto",
    "z-index": "auto",
    "overflow": "visible",
    "bbox": {
      "x": 0,
      "y": 80,
      "width": 1432,
      "height": 2233,
      "top": 80,
      "right": 1432,
      "bottom": 2313,
      "left": 0
    }
  },
  "row": {
    "tag": "DIV",
    "classes": "sc-c371c8f2-2 jqtfJg",
    "id": "",
    "text": "Apr 26, 05:55 PM\nedit\nEdit project\ndelete\nDelete project\nApr 26, 05:39 PM\nedit\nE",
    "background-color": "rgba(0, 0, 0, 0)",
    "background-image": "none",
    "color": "rgb(0, 0, 0)",
    "font-family": "\"Google Sans Text\"",
    "font-size": "16px",
    "font-weight": "400",
    "letter-spacing": "normal",
    "line-height": "24px",
    "padding": "0px 16px 16px 24px",
    "padding-top": "0px",
    "padding-right": "16px",
    "padding-bottom": "16px",
    "padding-left": "24px",
    "margin": "0px",
    "margin-top": "0px",
    "margin-right": "0px",
    "margin-bottom": "0px",
    "margin-left": "0px",
    "border": "0px none rgb(0, 0, 0)",
    "border-radius": "0px",
    "border-color": "rgb(0, 0, 0)",
    "border-width": "0px",
    "border-style": "none",
    "width": "1432px",
    "height": "319px",
    "max-width": "none",
    "min-width": "0px",
    "display": "flex",
    "grid-template-columns": "none",
    "grid-template-rows": "none",
    "gap": "16px",
    "flex-direction": "row",
    "justify-content": "center",
    "align-items": "normal",
    "box-shadow": "none",
    "backdrop-filter": "none",
    "opacity": "1",
    "position": "static",
    "top": "auto",
    "right": "auto",
    "bottom": "auto",
    "left": "auto",
    "z-index": "auto",
    "overflow": "visible",
    "bbox": {
      "x": 0,
      "y": 80,
      "width": 1432,
      "height": 319,
      "top": 80,
      "right": 1432,
      "bottom": 399,
      "left": 0
    }
  },
  "grid": {
    "tag": "DIV",
    "classes": "sc-c371c8f2-2 jqtfJg",
    "id": "",
    "text": "Apr 26, 05:55 PM\nedit\nEdit project\ndelete\nDelete project\nApr 26, 05:39 PM\nedit\nE",
    "background-color": "rgba(0, 0, 0, 0)",
    "background-image": "none",
    "color": "rgb(0, 0, 0)",
    "font-family": "\"Google Sans Text\"",
    "font-size": "16px",
    "font-weight": "400",
    "letter-spacing": "normal",
    "line-height": "24px",
    "padding": "0px 16px 16px 24px",
    "padding-top": "0px",
    "padding-right": "16px",
    "padding-bottom": "16px",
    "padding-left": "24px",
    "margin": "0px",
    "margin-top": "0px",
    "margin-right": "0px",
    "margin-bottom": "0px",
    "margin-left": "0px",
    "border": "0px none rgb(0, 0, 0)",
    "border-radius": "0px",
    "border-color": "rgb(0, 0, 0)",
    "border-width": "0px",
    "border-style": "none",
    "width": "1432px",
    "height": "319px",
    "max-width": "none",
    "min-width": "0px",
    "display": "flex",
    "grid-template-columns": "none",
    "grid-template-rows": "none",
    "gap": "16px",
    "flex-direction": "row",
    "justify-content": "center",
    "align-items": "normal",
    "box-shadow": "none",
    "backdrop-filter": "none",
    "opacity": "1",
    "position": "static",
    "top": "auto",
    "right": "auto",
    "bottom": "auto",
    "left": "auto",
    "z-index": "auto",
    "overflow": "visible",
    "bbox": {
      "x": 0,
      "y": 80,
      "width": 1432,
      "height": 319,
      "top": 80,
      "right": 1432,
      "bottom": 399,
      "left": 0
    }
  },
  "tile": {
    "tag": "DIV",
    "classes": "sc-7153f67b-0 diILxi",
    "id": "",
    "text": "Apr 26, 05:55 PM\nedit\nEdit project\ndelete\nDelete project",
    "background-color": "rgba(0, 0, 0, 0)",
    "background-image": "none",
    "color": "rgb(241, 243, 244)",
    "font-family": "\"Google Sans Text\"",
    "font-size": "16px",
    "font-weight": "400",
    "letter-spacing": "normal",
    "line-height": "24px",
    "padding": "0px",
    "padding-top": "0px",
    "padding-right": "0px",
    "padding-bottom": "0px",
    "padding-left": "0px",
    "margin": "0px",
    "margin-top": "0px",
    "margin-right": "0px",
    "margin-bottom": "0px",
    "margin-left": "0px",
    "border": "0px none rgb(241, 243, 244)",
    "border-radius": "16px",
    "border-color": "rgb(241, 243, 244)",
    "border-width": "0px",
    "border-style": "none",
    "width": "453.328px",
    "height": "302.984px",
    "max-width": "640px",
    "min-width": "auto",
    "display": "flex",
    "grid-template-columns": "none",
    "grid-template-rows": "none",
    "gap": "normal",
    "flex-direction": "column",
    "justify-content": "normal",
    "align-items": "normal",
    "box-shadow": "none",
    "backdrop-filter": "none",
    "opacity": "1",
    "position": "static",
    "top": "auto",
    "right": "auto",
    "bottom": "auto",
    "left": "auto",
    "z-index": "auto",
    "overflow": "visible",
    "bbox": {
      "x": 24,
      "y": 80,
      "width": 453.328125,
      "height": 302.984375,
      "top": 80,
      "right": 477.328125,
      "bottom": 382.984375,
      "left": 24
    }
  },
  "tileImg": {
    "tag": "IMG",
    "classes": "sc-7153f67b-2 fJUnJm",
    "id": "",
    "text": "",
    "background-color": "rgba(255, 255, 255, 0.15)",
    "background-image": "none",
    "color": "rgb(241, 243, 244)",
    "font-family": "\"Google Sans Text\"",
    "font-size": "16px",
    "font-weight": "400",
    "letter-spacing": "normal",
    "line-height": "24px",
    "padding": "0px",
    "padding-top": "0px",
    "padding-right": "0px",
    "padding-bottom": "0px",
    "padding-left": "0px",
    "margin": "0px",
    "margin-top": "0px",
    "margin-right": "0px",
    "margin-bottom": "0px",
    "margin-left": "0px",
    "border": "0px none rgb(241, 243, 244)",
    "border-radius": "16px",
    "border-color": "rgb(241, 243, 244)",
    "border-width": "0px",
    "border-style": "none",
    "width": "453.328px",
    "height": "254.984px",
    "max-width": "100%",
    "min-width": "0px",
    "display": "block",
    "grid-template-columns": "none",
    "grid-template-rows": "none",
    "gap": "normal",
    "flex-direction": "row",
    "justify-content": "normal",
    "align-items": "normal",
    "box-shadow": "none",
    "backdrop-filter": "none",
    "opacity": "1",
    "position": "static",
    "top": "auto",
    "right": "auto",
    "bottom": "auto",
    "left": "auto",
    "z-index": "auto",
    "overflow": "hidden",
    "bbox": {
      "x": 24,
      "y": 80,
      "width": 453.328125,
      "height": 254.984375,
      "top": 80,
      "right": 477.328125,
      "bottom": 334.984375,
      "left": 24
    }
  },
  "tileMeta": {
    "tag": "DIV",
    "classes": "sc-7153f67b-3 PhPkg",
    "id": "",
    "text": "Apr 26, 05:55 PM\nedit\nEdit project\ndelete\nDelete project",
    "background-color": "rgba(0, 0, 0, 0)",
    "background-image": "none",
    "color": "rgb(241, 243, 244)",
    "font-family": "\"Google Sans Text\"",
    "font-size": "16px",
    "font-weight": "400",
    "letter-spacing": "normal",
    "line-height": "24px",
    "padding": "4px 4px 4px 16px",
    "padding-top": "4px",
    "padding-right": "4px",
    "padding-bottom": "4px",
    "padding-left": "16px",
    "margin": "0px",
    "margin-top": "0px",
    "margin-right": "0px",
    "margin-bottom": "0px",
    "margin-left": "0px",
    "border": "0px none rgb(241, 243, 244)",
    "border-radius": "0px",
    "border-color": "rgb(241, 243, 244)",
    "border-width": "0px",
    "border-style": "none",
    "width": "453.328px",
    "height": "48px",
    "max-width": "none",
    "min-width": "auto",
    "display": "flex",
    "grid-template-columns": "none",
    "grid-template-rows": "none",
    "gap": "normal",
    "flex-direction": "row",
    "justify-content": "space-between",
    "align-items": "center",
    "box-shadow": "none",
    "backdrop-filter": "none",
    "opacity": "1",
    "position": "static",
    "top": "auto",
    "right": "auto",
    "bottom": "auto",
    "left": "auto",
    "z-index": "auto",
    "overflow": "visible",
    "bbox": {
      "x": 24,
      "y": 334.984375,
      "width": 453.328125,
      "height": 48,
      "top": 334.984375,
      "right": 477.328125,
      "bottom": 382.984375,
      "left": 24
    }
  },
  "tileDate": {
    "tag": "SPAN",
    "classes": "sc-7153f67b-5 fGigMq",
    "id": "",
    "text": "Apr 26, 05:55 PM\nedit\nEdit project",
    "background-color": "rgba(0, 0, 0, 0)",
    "background-image": "none",
    "color": "rgb(241, 243, 244)",
    "font-family": "\"Google Sans Text\"",
    "font-size": "16px",
    "font-weight": "400",
    "letter-spacing": "normal",
    "line-height": "24px",
    "padding": "0px",
    "padding-top": "0px",
    "padding-right": "0px",
    "padding-bottom": "0px",
    "padding-left": "0px",
    "margin": "0px",
    "margin-top": "0px",
    "margin-right": "0px",
    "margin-bottom": "0px",
    "margin-left": "0px",
    "border": "0px none rgb(241, 243, 244)",
    "border-radius": "0px",
    "border-color": "rgb(241, 243, 244)",
    "border-width": "0px",
    "border-style": "none",
    "width": "172.281px",
    "height": "40px",
    "max-width": "none",
    "min-width": "auto",
    "display": "flex",
    "grid-template-columns": "none",
    "grid-template-rows": "none",
    "gap": "8px",
    "flex-direction": "row",
    "justify-content": "normal",
    "align-items": "center",
    "box-shadow": "none",
    "backdrop-filter": "none",
    "opacity": "1",
    "position": "static",
    "top": "auto",
    "right": "auto",
    "bottom": "auto",
    "left": "auto",
    "z-index": "auto",
    "overflow": "visible",
    "bbox": {
      "x": 40,
      "y": 338.984375,
      "width": 172.28125,
      "height": 40,
      "top": 338.984375,
      "right": 212.28125,
      "bottom": 378.984375,
      "left": 40
    }
  },
  "tileLink": {
    "tag": "A",
    "classes": "",
    "id": "",
    "text": "",
    "background-color": "rgba(0, 0, 0, 0)",
    "background-image": "none",
    "color": "rgb(241, 243, 244)",
    "font-family": "\"Google Sans Text\"",
    "font-size": "16px",
    "font-weight": "400",
    "letter-spacing": "normal",
    "line-height": "24px",
    "padding": "0px",
    "padding-top": "0px",
    "padding-right": "0px",
    "padding-bottom": "0px",
    "padding-left": "0px",
    "margin": "0px",
    "margin-top": "0px",
    "margin-right": "0px",
    "margin-bottom": "0px",
    "margin-left": "0px",
    "border": "0px none rgb(241, 243, 244)",
    "border-radius": "0px",
    "border-color": "rgb(241, 243, 244)",
    "border-width": "0px",
    "border-style": "none",
    "width": "453.328px",
    "height": "254.984px",
    "max-width": "none",
    "min-width": "auto",
    "display": "block",
    "grid-template-columns": "none",
    "grid-template-rows": "none",
    "gap": "normal",
    "flex-direction": "row",
    "justify-content": "normal",
    "align-items": "normal",
    "box-shadow": "none",
    "backdrop-filter": "none",
    "opacity": "1",
    "position": "static",
    "top": "auto",
    "right": "auto",
    "bottom": "auto",
    "left": "auto",
    "z-index": "auto",
    "overflow": "visible",
    "bbox": {
      "x": 24,
      "y": 80,
      "width": 453.328125,
      "height": 254.984375,
      "top": 80,
      "right": 477.328125,
      "bottom": 334.984375,
      "left": 24
    }
  },
  "tilesPerRow": 9,
  "tileRects": [
    {
      "rect": {
        "x": 24,
        "y": 80,
        "width": 453.328125,
        "height": 302.984375,
        "top": 80,
        "right": 477.328125,
        "bottom": 382.984375,
        "left": 24
      }
    },
    {
      "rect": {
        "x": 493.328125,
        "y": 80,
        "width": 453.34375,
        "height": 303,
        "top": 80,
        "right": 946.671875,
        "bottom": 383,
        "left": 493.328125
      }
    },
    {
      "rect": {
        "x": 962.671875,
        "y": 80,
        "width": 453.328125,
        "height": 302.984375,
        "top": 80,
        "right": 1416,
        "bottom": 382.984375,
        "left": 962.671875
      }
    },
    {
      "rect": {
        "x": 24,
        "y": 399,
        "width": 453.328125,
        "height": 302.984375,
        "top": 399,
        "right": 477.328125,
        "bottom": 701.984375,
        "left": 24
      }
    },
    {
      "rect": {
        "x": 493.328125,
        "y": 399,
        "width": 453.34375,
        "height": 303,
        "top": 399,
        "right": 946.671875,
        "bottom": 702,
        "left": 493.328125
      }
    },
    {
      "rect": {
        "x": 962.671875,
        "y": 399,
        "width": 453.328125,
        "height": 302.984375,
        "top": 399,
        "right": 1416,
        "bottom": 701.984375,
        "left": 962.671875
      }
    },
    {
      "rect": {
        "x": 24,
        "y": 718,
        "width": 453.328125,
        "height": 302.984375,
        "top": 718,
        "right": 477.328125,
        "bottom": 1020.984375,
        "left": 24
      }
    },
    {
      "rect": {
        "x": 493.328125,
        "y": 718,
        "width": 453.34375,
        "height": 303,
        "top": 718,
        "right": 946.671875,
        "bottom": 1021,
        "left": 493.328125
      }
    },
    {
      "rect": {
        "x": 962.671875,
        "y": 718,
        "width": 453.328125,
        "height": 302.984375,
        "top": 718,
        "right": 1416,
        "bottom": 1020.984375,
        "left": 962.671875
      }
    }
  ],
  "newProj": {
    "tag": "HTML",
    "classes": "",
    "id": "",
    "text": "Flow\ntv\nFlow TV\nhelp_outlined\nFlow Help Center\nFlow Help Center\nmore_vert\nULTRA\n",
    "background-color": "rgb(0, 0, 0)",
    "background-image": "none",
    "color": "rgb(0, 0, 0)",
    "font-family": "\"Google Sans Text\"",
    "font-size": "16px",
    "font-weight": "400",
    "letter-spacing": "normal",
    "line-height": "24px",
    "padding": "0px",
    "padding-top": "0px",
    "padding-right": "0px",
    "padding-bottom": "0px",
    "padding-left": "0px",
    "margin": "0px",
    "margin-top": "0px",
    "margin-right": "0px",
    "margin-bottom": "0px",
    "margin-left": "0px",
    "border": "0px none rgb(0, 0, 0)",
    "border-radius": "0px",
    "border-color": "rgb(0, 0, 0)",
    "border-width": "0px",
    "border-style": "none",
    "width": "1440px",
    "height": "900px",
    "max-width": "none",
    "min-width": "0px",
    "display": "block",
    "grid-template-columns": "none",
    "grid-template-rows": "none",
    "gap": "normal",
    "flex-direction": "row",
    "justify-content": "normal",
    "align-items": "normal",
    "box-shadow": "none",
    "backdrop-filter": "none",
    "opacity": "1",
    "position": "static",
    "top": "auto",
    "right": "auto",
    "bottom": "auto",
    "left": "auto",
    "z-index": "auto",
    "overflow": "visible",
    "bbox": {
      "x": 0,
      "y": 0,
      "width": 1440,
      "height": 900,
      "top": 0,
      "right": 1440,
      "bottom": 900,
      "left": 0
    }
  },
  "ultra": {
    "tag": "BUTTON",
    "classes": "sc-46b056f6-7 dhpCJo",
    "id": "",
    "text": "ULTRA",
    "background-color": "rgba(0, 0, 0, 0)",
    "background-image": "none",
    "color": "rgb(241, 243, 244)",
    "font-family": "\"Google Sans Text\"",
    "font-size": "16px",
    "font-weight": "400",
    "letter-spacing": "normal",
    "line-height": "24px",
    "padding": "8px",
    "padding-top": "8px",
    "padding-right": "8px",
    "padding-bottom": "8px",
    "padding-left": "8px",
    "margin": "0px",
    "margin-top": "0px",
    "margin-right": "0px",
    "margin-bottom": "0px",
    "margin-left": "0px",
    "border": "1px solid rgba(255, 255, 255, 0.05)",
    "border-radius": "16px",
    "border-color": "rgba(255, 255, 255, 0.05)",
    "border-width": "1px",
    "border-style": "solid",
    "width": "111.047px",
    "height": "48px",
    "max-width": "none",
    "min-width": "auto",
    "display": "flex",
    "grid-template-columns": "none",
    "grid-template-rows": "none",
    "gap": "8px",
    "flex-direction": "row",
    "justify-content": "normal",
    "align-items": "center",
    "box-shadow": "none",
    "backdrop-filter": "none",
    "opacity": "1",
    "position": "static",
    "top": "auto",
    "right": "auto",
    "bottom": "auto",
    "left": "auto",
    "z-index": "auto",
    "overflow": "visible",
    "bbox": {
      "x": 1304.953125,
      "y": 16,
      "width": 111.046875,
      "height": 48,
      "top": 16,
      "right": 1416,
      "bottom": 64,
      "left": 1304.953125
    }
  },
  "viewport": {
    "w": 1440,
    "h": 900
  }
}